fastjet/__init__.py
fastjet/_ext.cpython-312-aarch64-linux-musl.so
fastjet/_generalevent.py
fastjet/_multievent.py
fastjet/_pyjet.py
fastjet/_singleevent.py
fastjet/_utils.py
fastjet/version.py
fastjet/_swig/__init__.py
fastjet/_swig/_fastjet_swig.cpython-312-aarch64-linux-musl.so
fastjet/bin/fastjet-config
fastjet/include/fastjet/ATLASConePlugin.hh
fastjet/include/fastjet/ActiveAreaSpec.hh
fastjet/include/fastjet/AreaDefinition.hh
fastjet/include/fastjet/CDFJetCluPlugin.hh
fastjet/include/fastjet/CDFMidPointPlugin.hh
fastjet/include/fastjet/CMSIterativeConePlugin.hh
fastjet/include/fastjet/CircularRange.hh
fastjet/include/fastjet/ClusterSequence.hh
fastjet/include/fastjet/ClusterSequence1GhostPassiveArea.hh
fastjet/include/fastjet/ClusterSequenceActiveArea.hh
fastjet/include/fastjet/ClusterSequenceActiveAreaExplicitGhosts.hh
fastjet/include/fastjet/ClusterSequenceArea.hh
fastjet/include/fastjet/ClusterSequenceAreaBase.hh
fastjet/include/fastjet/ClusterSequencePassiveArea.hh
fastjet/include/fastjet/ClusterSequenceStructure.hh
fastjet/include/fastjet/ClusterSequenceVoronoiArea.hh
fastjet/include/fastjet/ClusterSequenceWithArea.hh
fastjet/include/fastjet/CompositeJetStructure.hh
fastjet/include/fastjet/D0RunIBaseConePlugin.hh
fastjet/include/fastjet/D0RunIConePlugin.hh
fastjet/include/fastjet/D0RunIIConePlugin.hh
fastjet/include/fastjet/D0RunIpre96ConePlugin.hh
fastjet/include/fastjet/EECambridgePlugin.hh
fastjet/include/fastjet/Error.hh
fastjet/include/fastjet/FunctionOfPseudoJet.hh
fastjet/include/fastjet/GhostedAreaSpec.hh
fastjet/include/fastjet/GridJetPlugin.hh
fastjet/include/fastjet/JadePlugin.hh
fastjet/include/fastjet/JetDefinition.hh
fastjet/include/fastjet/LimitedWarning.hh
fastjet/include/fastjet/NNBase.hh
fastjet/include/fastjet/NNFJN2Plain.hh
fastjet/include/fastjet/NNFJN2Tiled.hh
fastjet/include/fastjet/NNH.hh
fastjet/include/fastjet/NestedDefsPlugin.hh
fastjet/include/fastjet/PseudoJet.hh
fastjet-3.5.1.1.dist-info/METADATA
fastjet-3.5.1.1.dist-info/WHEEL
fastjet-3.5.1.1.dist-info/RECORD
fastjet-3.5.1.1.dist-info/licenses/LICENSE
