Metadata-Version: 2.4
Name: fastjet
Version: 3.5.1.1
License-Expression: BSD-3-Clause
License-File: LICENSE
Classifier: Development Status :: 1 - Planning
Classifier: Intended Audience :: Developers
Classifier: Intended Audience :: Science/Research
Classifier: Operating System :: MacOS :: MacOS X
Classifier: Operating System :: POSIX :: Linux
Classifier: Programming Language :: Python
Classifier: Programming Language :: Python :: 3
Classifier: Programming Language :: Python :: 3 :: Only
Classifier: Topic :: Scientific/Engineering
Requires-Python: >=3.9
Requires-Dist: awkward>=2
Requires-Dist: numpy>=1.13.3
Requires-Dist: vector
Provides-Extra: local-build
Requires-Dist: scikit-build-core>=0.11; extra == "local-build"
Requires-Dist: setuptools-scm; extra == "local-build"
Provides-Extra: dask
Requires-Dist: dask>=2023.4.0; extra == "dask"
Requires-Dist: dask-awkward>=2023.4.2; extra == "dask"
Provides-Extra: dev
Requires-Dist: pytest>=4.6; extra == "dev"
Provides-Extra: docs
Requires-Dist: Sphinx>=3.0.0; extra == "docs"
Requires-Dist: recommonmark>=0.5.0; extra == "docs"
Requires-Dist: sphinx-copybutton; extra == "docs"
Requires-Dist: sphinx-rtd-theme>=0.5.0; extra == "docs"
Provides-Extra: test
Requires-Dist: pytest>=4.6; extra == "test"
Requires-Dist: uproot>=5; extra == "test"
Requires-Dist: dask>=2023.4.0; python_version > "3.7" and extra == "test"
Requires-Dist: dask-awkward[test]>=2023.4.2; python_version > "3.7" and extra == "test"
Requires-Dist: distributed>=2023.4.0; python_version > "3.7" and extra == "test"
